happytorch/__init__.py
happytorch/configs.py
happytorch/logger.py
happytorch/utils2.py
happytorch/Timeline-master/make_timeline.py
happytorch/files/delete_dot_underscore.py
happytorch/files/frames2videos.py
happytorch/plots/log_analysis.py
happytorch/plots/vis_label.py
happytorch/train/Trainer.py
happytorch/train/__init__.py
happytorch/train/data.py
happytorch/train/utils.py
happytorch/visualization/__init__.py
happytorch/visualization/backup_score_curve.py
happytorch/visualization/score_curve.py
happytorch/visualization/src_imgs.py
happytorch/visualization/test.py
happytorch/visualization/trans2length.py
happytorch-0.0.4.dist-info/LICENSE
happytorch-0.0.4.dist-info/METADATA
happytorch-0.0.4.dist-info/WHEEL
happytorch-0.0.4.dist-info/top_level.txt
happytorch-0.0.4.dist-info/RECORD
