Metadata-Version: 2.1
Name: happytorch
Version: 0.0.4
Summary: A small example package
Author-email: 2-mo <mo1031@live.com>
Project-URL: Homepage, https://github.com/pypa/sampleproject
Project-URL: Issues, https://github.com/pypa/sampleproject/issues
Classifier: Programming Language :: Python :: 3
Classifier: License :: OSI Approved :: MIT License
Classifier: Operating System :: OS Independent
Requires-Python: >=3.8
License-File: LICENSE
Requires-Dist: torch
Requires-Dist: numpy
Requires-Dist: pyyaml
Requires-Dist: opencv-python
Requires-Dist: matplotlib
